django_otp_webauthn/__init__.py
django_otp_webauthn/admin.py
django_otp_webauthn/apps.py
django_otp_webauthn/backends.py
django_otp_webauthn/checks.py
django_otp_webauthn/exceptions.py
django_otp_webauthn/helpers.py
django_otp_webauthn/models.py
django_otp_webauthn/settings.py
django_otp_webauthn/urls.py
django_otp_webauthn/utils.py
django_otp_webauthn/views.py
django_otp_webauthn/locale/de/LC_MESSAGES/django.mo
django_otp_webauthn/locale/de/LC_MESSAGES/django.po
django_otp_webauthn/locale/de/LC_MESSAGES/djangojs.mo
django_otp_webauthn/locale/de/LC_MESSAGES/djangojs.po
django_otp_webauthn/locale/es/LC_MESSAGES/django.mo
django_otp_webauthn/locale/es/LC_MESSAGES/django.po
django_otp_webauthn/locale/es/LC_MESSAGES/djangojs.mo
django_otp_webauthn/locale/es/LC_MESSAGES/djangojs.po
django_otp_webauthn/locale/it/LC_MESSAGES/django.mo
django_otp_webauthn/locale/it/LC_MESSAGES/django.po
django_otp_webauthn/locale/it/LC_MESSAGES/djangojs.mo
django_otp_webauthn/locale/it/LC_MESSAGES/djangojs.po
django_otp_webauthn/locale/nl/LC_MESSAGES/django.mo
django_otp_webauthn/locale/nl/LC_MESSAGES/django.po
django_otp_webauthn/locale/nl/LC_MESSAGES/djangojs.mo
django_otp_webauthn/locale/nl/LC_MESSAGES/djangojs.po
django_otp_webauthn/migrations/0001_initial.py
django_otp_webauthn/migrations/0001_squashed_0003_webauthncredential_hash_binary_to_hex.py
django_otp_webauthn/migrations/0002_timestamps.py
django_otp_webauthn/migrations/0003_webauthncredential_hash_binary_to_hex.py
django_otp_webauthn/migrations/0004_webauthnuserhandle.py
django_otp_webauthn/migrations/__init__.py
django_otp_webauthn/static/django_otp_webauthn/otp_webauthn_auth.js
django_otp_webauthn/static/django_otp_webauthn/otp_webauthn_auth.js.map
django_otp_webauthn/static/django_otp_webauthn/otp_webauthn_register.js
django_otp_webauthn/static/django_otp_webauthn/otp_webauthn_register.js.map
django_otp_webauthn/templates/django_otp_webauthn/auth_scripts.html
django_otp_webauthn-0.8.0.dist-info/METADATA
django_otp_webauthn-0.8.0.dist-info/WHEEL
django_otp_webauthn-0.8.0.dist-info/licenses/LICENSE
django_otp_webauthn-0.8.0.dist-info/RECORD
