Metadata-Version: 2.4
Name: django-otp-webauthn
Version: 0.8.0
Summary: FIDO2 WebAuthn support for django-otp: lets your users authenticate with Passkeys
Project-URL: Changelog, https://github.com/Stormbase/django-otp-webauthn/blob/main/CHANGELOG.md
Project-URL: Documentation, https://django-otp-webauthn.readthedocs.io/en/latest/
Project-URL: Issues, https://github.com/Stormbase/django-otp-webauthn/issues
Project-URL: Source, https://github.com/Stormbase/django-otp-webauthn
Author-email: "Storm B. Heg" <storm@stormbase.digital>
License-Expression: BSD-3-Clause
License-File: LICENSE
Keywords: authentication,django,django-otp,fido2,mfa,security,u2f,webauthn
Classifier: Development Status :: 4 - Beta
Classifier: Environment :: Web Environment
Classifier: Framework :: Django
Classifier: Framework :: Django :: 4.2
Classifier: Framework :: Django :: 5.1
Classifier: Framework :: Django :: 5.2
Classifier: Framework :: Django :: 6.0
Classifier: Intended Audience :: Developers
Classifier: License :: OSI Approved :: BSD License
Classifier: Operating System :: OS Independent
Classifier: Programming Language :: Python
Classifier: Programming Language :: Python :: 3 :: Only
Classifier: Programming Language :: Python :: 3.10
Classifier: Programming Language :: Python :: 3.11
Classifier: Programming Language :: Python :: 3.12
Classifier: Programming Language :: Python :: 3.13
Classifier: Programming Language :: Python :: 3.14
Classifier: Topic :: Communications :: FIDO
Classifier: Topic :: Security
Requires-Python: >=3.10
Requires-Dist: django-otp<2,>=1.4
Requires-Dist: django>=4.2
Requires-Dist: djangorestframework>=3.14
Requires-Dist: webauthn<3,>=2.6
Provides-Extra: docs
Requires-Dist: furo==2024.8.6; extra == 'docs'
Requires-Dist: pyspelling==2.10; extra == 'docs'
Requires-Dist: sphinx-autobuild==2024.10.3; extra == 'docs'
Requires-Dist: sphinx-copybutton==0.5.2; extra == 'docs'
Requires-Dist: sphinx-design==0.6.1; extra == 'docs'
Requires-Dist: sphinx==8.0.2; extra == 'docs'
Provides-Extra: playwright
Requires-Dist: playwright<2,>=1.49; extra == 'playwright'
Requires-Dist: pytest-playwright<1,>=0.5.2; extra == 'playwright'
Provides-Extra: testing
Requires-Dist: beautifulsoup4<5,>=4; extra == 'testing'
Requires-Dist: coverage[toml]<8,>=7; extra == 'testing'
Requires-Dist: dj-database-url<4,>=3; extra == 'testing'
Requires-Dist: django-csp<5,>=4; extra == 'testing'
Requires-Dist: django-debug-toolbar<7,>=6; extra == 'testing'
Requires-Dist: jsonschema~=4.23; extra == 'testing'
Requires-Dist: pytest-django<5,>4.5; extra == 'testing'
Requires-Dist: pytest-env<2,>=1; extra == 'testing'
Requires-Dist: pytest-factoryboy<3,>=2; extra == 'testing'
Requires-Dist: pytest-mock<4,>=3.14; extra == 'testing'
Requires-Dist: pytest-randomly<5,>=4; extra == 'testing'
Requires-Dist: pytest-rerunfailures<17,>=16; extra == 'testing'
Requires-Dist: pytest<9,>8; extra == 'testing'
